odoo/addons/metadata/__init__.py
odoo/addons/metadata/__manifest__.py
odoo/addons/metadata/models/__init__.py
odoo/addons/metadata/models/metadata_line.py
odoo/addons/metadata/security/ir.model.access.csv
odoo14_addon_metadata-14.0.1.0.0.dist-info/METADATA
odoo14_addon_metadata-14.0.1.0.0.dist-info/WHEEL
odoo14_addon_metadata-14.0.1.0.0.dist-info/top_level.txt
odoo14_addon_metadata-14.0.1.0.0.dist-info/RECORD
